afritextai/__init__.py
afritextai/__version__.py
afritextai/afritextai_types.py
afritextai/client.py
afritextai/transcriber.py
afritextai/utils.py
aspeechai/__init__.py
aspeechai/__version__.py
aspeechai/aspeechai_types.py
aspeechai/client.py
aspeechai/transcriber.py
aspeechai/utils.py
aspeechai-0.1.0.dist-info/METADATA
aspeechai-0.1.0.dist-info/WHEEL
aspeechai-0.1.0.dist-info/top_level.txt
aspeechai-0.1.0.dist-info/RECORD
