Metadata-Version: 2.1
Name: aspeechai
Version: 0.1.0
Summary: ASpeechAI Python SDK
Home-page: https://github.com/ASpeechAI/aspeechai-python-sdk
Author: ASpeechAI
Author-email: contact@a-speechai.com
License: UNKNOWN
Platform: UNKNOWN
Classifier: Development Status :: 4 - Beta
Classifier: Intended Audience :: Developers
Classifier: License :: OSI Approved :: MIT License
Classifier: Programming Language :: Python :: 3
Classifier: Programming Language :: Python :: 3.10
Requires-Python: >=3.10
Requires-Dist: httpx (>=0.19.0)
Requires-Dist: pydantic (>=2.9.2)
Requires-Dist: typing-extensions (>=3.7)
Requires-Dist: websockets (>=11.0)
Provides-Extra: extras
Requires-Dist: pyaudio (>=0.2.13) ; extra == 'extras'
